rl8/__init__.py
rl8/__main__.py
rl8/_utils.py
rl8/conditions.py
rl8/data.py
rl8/distributions.py
rl8/env.py
rl8/schedulers.py
rl8/views.py
rl8/algorithms/__init__.py
rl8/algorithms/_base.py
rl8/algorithms/_feedforward.py
rl8/algorithms/_recurrent.py
rl8/models/__init__.py
rl8/models/_base.py
rl8/models/_feedforward.py
rl8/models/_recurrent.py
rl8/nn/__init__.py
rl8/nn/functional.py
rl8/nn/modules/__init__.py
rl8/nn/modules/activations.py
rl8/nn/modules/attention.py
rl8/nn/modules/embeddings.py
rl8/nn/modules/mlp.py
rl8/nn/modules/module.py
rl8/nn/modules/perceiver.py
rl8/nn/modules/skip.py
rl8/policies/__init__.py
rl8/policies/_base.py
rl8/policies/_feedforward.py
rl8/policies/_recurrent.py
rl8/trainers/__init__.py
rl8/trainers/_base.py
rl8/trainers/_feedforward.py
rl8/trainers/_recurrent.py
rl8/trainers/config.py
rl8-0.3.0.dist-info/licenses/LICENSE
rl8-0.3.0.dist-info/METADATA
rl8-0.3.0.dist-info/WHEEL
rl8-0.3.0.dist-info/entry_points.txt
rl8-0.3.0.dist-info/top_level.txt
rl8-0.3.0.dist-info/RECORD
