Metadata-Version: 2.4
Name: rl8
Version: 0.3.0
Summary: A high throughput, end-to-end RL library for infinite horizon tasks.
Author: Andrew B.
License:                                  Apache License
Project-URL: Repository, https://github.com/theOGognf/rl8
Classifier: Intended Audience :: Science/Research
Classifier: Intended Audience :: Developers
Classifier: License :: OSI Approved :: Apache Software License
Classifier: Operating System :: POSIX
Classifier: Operating System :: Unix
Classifier: Programming Language :: Python :: 3.10
Classifier: Programming Language :: Python :: 3.11
Classifier: Topic :: Software Development
Classifier: Topic :: Scientific/Engineering
Classifier: Typing :: Typed
Requires-Python: >=3.10
License-File: LICENSE
Requires-Dist: mlflow-skinny==2.*
Requires-Dist: pandas==2.*
Requires-Dist: psutil==5.*
Requires-Dist: torchrl==0.*
Requires-Dist: typing-extensions
Provides-Extra: dev
Requires-Dist: build[virtualenv]; extra == "dev"
Requires-Dist: mypy; extra == "dev"
Requires-Dist: pre-commit; extra == "dev"
Requires-Dist: pytest; extra == "dev"
Requires-Dist: pytest-cov; extra == "dev"
Requires-Dist: pytest-xdist; extra == "dev"
Requires-Dist: pytest-randomly; extra == "dev"
Requires-Dist: sphinx; extra == "dev"
Requires-Dist: tox; extra == "dev"
Requires-Dist: types-PyYAML; extra == "dev"
Requires-Dist: virtualenv; extra == "dev"
Dynamic: license-file
